gitguard/__init__.py
gitguard/gemini.py
gitguard/git_ops.py
gitguard/main.py
gitguard_cli-0.1.2.dist-info/licenses/LICENSE
gitguard_cli-0.1.2.dist-info/METADATA
gitguard_cli-0.1.2.dist-info/WHEEL
gitguard_cli-0.1.2.dist-info/entry_points.txt
gitguard_cli-0.1.2.dist-info/top_level.txt
gitguard_cli-0.1.2.dist-info/RECORD
