Metadata-Version: 2.4
Name: gitguard-cli
Version: 0.1.2
Summary: Natural language to Git commands - safely generate, explain, and run Git operations from your terminal
Author-email: ashvp <ashwin.vp.2005@gmail.com>
License-Expression: MIT
Project-URL: Homepage, https://github.com/ashvp/gitguard
Project-URL: Repository, https://github.com/ashvp/gitguard
Project-URL: Issues, https://github.com/ashvp/gitguard/issues
Keywords: git,cli,ai,security,developer-tools
Classifier: Development Status :: 3 - Alpha
Classifier: Intended Audience :: Developers
Classifier: Programming Language :: Python :: 3
Classifier: Programming Language :: Python :: 3.9
Classifier: Environment :: Console
Requires-Python: >=3.9
License-File: LICENSE
Requires-Dist: gitpython>=3.1.45
Requires-Dist: google-genai>=0.3.0
Requires-Dist: python-dotenv>=1.2.1
Requires-Dist: rich>=14.2.0
Requires-Dist: typer>=0.21.0
Requires-Dist: pydantic>=2.0.0
Dynamic: license-file
